Metadata-Version: 1.0
Name: mongo-observer
Version: 0.0.1
Summary: UNKNOWN
Home-page: https://github.com/diogommartins/mongo_observer
Author: Diogo Magalhaes Martins
Author-email: magalhaesmartins@icloud.com
License: UNKNOWN
Keywords: collection mongodb oplog observer livecollection meteor
Platform: UNKNOWN
